exif2timestream.py
setup.py
exif2timestream.egg-info/PKG-INFO
exif2timestream.egg-info/SOURCES.txt
exif2timestream.egg-info/dependency_links.txt
exif2timestream.egg-info/requires.txt
exif2timestream.egg-info/top_level.txt
test/test_exif2timestream.py