Metadata-Version: 1.1
Name: exif2timestream
Version: 0.1.1
Summary: 
